cashocs/__init__.py
cashocs/_exceptions.py
cashocs/_typing.py
cashocs/log.py
cashocs/mpi.py
cashocs/verification.py
cashocs/_cli/__init__.py
cashocs/_cli/_convert.py
cashocs/_cli/_extract_mesh.py
cashocs/_constraints/__init__.py
cashocs/_constraints/constrained_problems.py
cashocs/_constraints/constraints.py
cashocs/_constraints/deflated_problems.py
cashocs/_constraints/solvers.py
cashocs/_database/__init__.py
cashocs/_database/database.py
cashocs/_database/form_database.py
cashocs/_database/function_database.py
cashocs/_database/geometry_database.py
cashocs/_database/parameter_database.py
cashocs/_forms/__init__.py
cashocs/_forms/control_form_handler.py
cashocs/_forms/form_handler.py
cashocs/_forms/general_form_handler.py
cashocs/_forms/shape_form_handler.py
cashocs/_forms/shape_regularization.py
cashocs/_optimization/__init__.py
cashocs/_optimization/cost_functional.py
cashocs/_optimization/optimization_problem.py
cashocs/_optimization/optimization_variable_abstractions.py
cashocs/_optimization/line_search/__init__.py
cashocs/_optimization/line_search/armijo_line_search.py
cashocs/_optimization/line_search/line_search.py
cashocs/_optimization/line_search/polynomial_line_search.py
cashocs/_optimization/optimal_control/__init__.py
cashocs/_optimization/optimal_control/box_constraints.py
cashocs/_optimization/optimal_control/control_variable_abstractions.py
cashocs/_optimization/optimal_control/optimal_control_problem.py
cashocs/_optimization/optimization_algorithms/__init__.py
cashocs/_optimization/optimization_algorithms/callback.py
cashocs/_optimization/optimization_algorithms/gradient_descent.py
cashocs/_optimization/optimization_algorithms/l_bfgs.py
cashocs/_optimization/optimization_algorithms/ncg.py
cashocs/_optimization/optimization_algorithms/newton.py
cashocs/_optimization/optimization_algorithms/optimization_algorithm.py
cashocs/_optimization/shape_optimization/__init__.py
cashocs/_optimization/shape_optimization/shape_optimization_problem.py
cashocs-2.8.1.dist-info/licenses/COPYING
cashocs-2.8.1.dist-info/METADATA
cashocs-2.8.1.dist-info/WHEEL
cashocs-2.8.1.dist-info/entry_points.txt
cashocs-2.8.1.dist-info/top_level.txt
cashocs-2.8.1.dist-info/RECORD
