Metadata-Version: 2.4
Name: cashocs
Version: 2.8.1
Summary: Computational Adjoint-Based Shape Optimization and Optimal Control Software
Author: Sebastian Blauth
Author-email: sebastian.blauth@itwm.fraunhofer.de
License: GNU General Public License v3 or later (GPLv3+)
Project-URL: Documentation, https://cashocs.readthedocs.io/en/stable
Project-URL: Source, https://github.com/sblauth/cashocs
Project-URL: Tutorial, https://cashocs.readthedocs.io/en/stable/user
Project-URL: Tracker, https://github.com/sblauth/cashocs/issues
Keywords: Shape Optimization,Optimal Control,FEniCS,Optimization,PDE,Adjoint,Finite Element Method
Classifier: Topic :: Scientific/Engineering
Classifier: Topic :: Scientific/Engineering :: Mathematics
Classifier: Development Status :: 5 - Production/Stable
Classifier: Intended Audience :: Developers
Classifier: Intended Audience :: Education
Classifier: Intended Audience :: End Users/Desktop
Classifier: Intended Audience :: Science/Research
Classifier: Programming Language :: Python :: 3
Classifier: Programming Language :: Python :: 3.10
Classifier: Programming Language :: Python :: 3.11
Classifier: Programming Language :: Python :: 3.12
Classifier: Programming Language :: Python :: 3.13
Classifier: Programming Language :: Python :: 3.14
Classifier: Programming Language :: Python :: 3 :: Only
Classifier: License :: OSI Approved :: GNU General Public License v3 or later (GPLv3+)
Classifier: Operating System :: OS Independent
Requires-Python: >=3.10
License-File: COPYING
Requires-Dist: meshio>=4.1.0
Requires-Dist: numpy
Requires-Dist: scipy>=1.10.0
Requires-Dist: typing_extensions
Requires-Dist: matplotlib
Provides-Extra: tests
Requires-Dist: pytest; extra == "tests"
Requires-Dist: pytest-randomly; extra == "tests"
Requires-Dist: pytest-cov; extra == "tests"
Requires-Dist: pytest-xdist; extra == "tests"
Requires-Dist: pytest-timeout; extra == "tests"
Requires-Dist: pytest-icdiff; extra == "tests"
Provides-Extra: docs
Requires-Dist: sphinx; extra == "docs"
Requires-Dist: pydata-sphinx-theme; extra == "docs"
Requires-Dist: sphinx-argparse; extra == "docs"
Requires-Dist: sphinx-copybutton; extra == "docs"
Requires-Dist: sphinx-design; extra == "docs"
Requires-Dist: jupytext; extra == "docs"
Requires-Dist: myst-parser; extra == "docs"
Provides-Extra: all
Requires-Dist: cashocs[docs,tests]; extra == "all"
Dynamic: license-file
